timedsort/__init__.py
timedsort/timedsort.py
timedsorts-0.0.2.dist-info/LICENSE
timedsorts-0.0.2.dist-info/METADATA
timedsorts-0.0.2.dist-info/WHEEL
timedsorts-0.0.2.dist-info/top_level.txt
timedsorts-0.0.2.dist-info/RECORD
