Metadata-Version: 2.1
Name: timedsorts
Version: 0.0.2
Summary: my first package that focuses on sorting algorithms
Home-page: https://github.com/BentoOre0/timedsort-python
Author: Jeremy Yu
Author-email: jeremy.yu@britishschoolmanila.org
Project-URL: Bug Tracker, https://github.com/pypa/sampleproject/issues
Classifier: Programming Language :: Python :: 3
Classifier: License :: OSI Approved :: MIT License
Classifier: Operating System :: OS Independent
Requires-Python: >=3.6
License-File: LICENSE
